{
  "id": "af01ec09-2f78-452a-9712-06ad83afecaa",
  "prevId": "e763ff64-68ca-4132-9eb1-2aba259126e5",
  "version": "7",
  "dialect": "postgresql",
  "tables": {
    "public.account": {
      "name": "account",
      "schema": "",
      "columns": {
        "user_id": {
          "name": "user_id",
          "type": "varchar(255)",
          "primaryKey": false,
          "notNull": true
        },
        "type": {
          "name": "type",
          "type": "varchar(255)",
          "primaryKey": false,
          "notNull": true
        },
        "provider": {
          "name": "provider",
          "type": "varchar(255)",
          "primaryKey": false,
          "notNull": true
        },
        "provider_account_id": {
          "name": "provider_account_id",
          "type": "varchar(255)",
          "primaryKey": false,
          "notNull": true
        },
        "refresh_token": {
          "name": "refresh_token",
          "type": "text",
          "primaryKey": false,
          "notNull": false
        },
        "access_token": {
          "name": "access_token",
          "type": "text",
          "primaryKey": false,
          "notNull": false
        },
        "expires_at": {
          "name": "expires_at",
          "type": "integer",
          "primaryKey": false,
          "notNull": false
        },
        "token_type": {
          "name": "token_type",
          "type": "varchar(255)",
          "primaryKey": false,
          "notNull": false
        },
        "scope": {
          "name": "scope",
          "type": "varchar(255)",
          "primaryKey": false,
          "notNull": false
        },
        "id_token": {
          "name": "id_token",
          "type": "text",
          "primaryKey": false,
          "notNull": false
        },
        "session_state": {
          "name": "session_state",
          "type": "varchar(255)",
          "primaryKey": false,
          "notNull": false
        }
      },
      "indexes": {
        "account_user_id_idx": {
          "name": "account_user_id_idx",
          "columns": [
            {
              "expression": "user_id",
              "isExpression": false,
              "asc": true,
              "nulls": "last"
            }
          ],
          "isUnique": false,
          "concurrently": false,
          "method": "btree",
          "with": {}
        }
      },
      "foreignKeys": {
        "account_user_id_user_id_fk": {
          "name": "account_user_id_user_id_fk",
          "tableFrom": "account",
          "tableTo": "user",
          "columnsFrom": [
            "user_id"
          ],
          "columnsTo": [
            "id"
          ],
          "onDelete": "no action",
          "onUpdate": "no action"
        }
      },
      "compositePrimaryKeys": {
        "account_provider_provider_account_id_pk": {
          "name": "account_provider_provider_account_id_pk",
          "columns": [
            "provider",
            "provider_account_id"
          ]
        }
      },
      "uniqueConstraints": {}
    },
    "public.course": {
      "name": "course",
      "schema": "",
      "columns": {
        "id": {
          "name": "id",
          "type": "varchar(255)",
          "primaryKey": true,
          "notNull": true
        },
        "name": {
          "name": "name",
          "type": "varchar(256)",
          "primaryKey": false,
          "notNull": false
        },
        "slug": {
          "name": "slug",
          "type": "varchar(25)",
          "primaryKey": false,
          "notNull": true
        },
        "description": {
          "name": "description",
          "type": "text",
          "primaryKey": false,
          "notNull": false
        },
        "owner_id": {
          "name": "owner_id",
          "type": "varchar(255)",
          "primaryKey": false,
          "notNull": true
        },
        "start_date": {
          "name": "start_date",
          "type": "timestamp with time zone",
          "primaryKey": false,
          "notNull": true
        },
        "end_date": {
          "name": "end_date",
          "type": "timestamp with time zone",
          "primaryKey": false,
          "notNull": true
        },
        "created_at": {
          "name": "created_at",
          "type": "timestamp with time zone",
          "primaryKey": false,
          "notNull": true,
          "default": "CURRENT_TIMESTAMP"
        },
        "updated_at": {
          "name": "updated_at",
          "type": "timestamp with time zone",
          "primaryKey": false,
          "notNull": false
        }
      },
      "indexes": {},
      "foreignKeys": {
        "course_owner_id_user_id_fk": {
          "name": "course_owner_id_user_id_fk",
          "tableFrom": "course",
          "tableTo": "user",
          "columnsFrom": [
            "owner_id"
          ],
          "columnsTo": [
            "id"
          ],
          "onDelete": "no action",
          "onUpdate": "no action"
        }
      },
      "compositePrimaryKeys": {},
      "uniqueConstraints": {
        "course_slug_unique": {
          "name": "course_slug_unique",
          "nullsNotDistinct": false,
          "columns": [
            "slug"
          ]
        }
      }
    },
    "public.lesson_assistances": {
      "name": "lesson_assistances",
      "schema": "",
      "columns": {
        "id": {
          "name": "id",
          "type": "varchar(255)",
          "primaryKey": true,
          "notNull": true
        },
        "lessonId": {
          "name": "lessonId",
          "type": "varchar(255)",
          "primaryKey": false,
          "notNull": true
        },
        "assisted": {
          "name": "assisted",
          "type": "boolean",
          "primaryKey": false,
          "notNull": false
        },
        "studentId": {
          "name": "studentId",
          "type": "varchar(255)",
          "primaryKey": false,
          "notNull": true
        },
        "createdAt": {
          "name": "createdAt",
          "type": "timestamp with time zone",
          "primaryKey": false,
          "notNull": true,
          "default": "CURRENT_TIMESTAMP"
        },
        "updatedAt": {
          "name": "updatedAt",
          "type": "timestamp with time zone",
          "primaryKey": false,
          "notNull": false
        }
      },
      "indexes": {},
      "foreignKeys": {
        "lesson_assistances_lessonId_lesson_id_fk": {
          "name": "lesson_assistances_lessonId_lesson_id_fk",
          "tableFrom": "lesson_assistances",
          "tableTo": "lesson",
          "columnsFrom": [
            "lessonId"
          ],
          "columnsTo": [
            "id"
          ],
          "onDelete": "no action",
          "onUpdate": "no action"
        },
        "lesson_assistances_studentId_user_id_fk": {
          "name": "lesson_assistances_studentId_user_id_fk",
          "tableFrom": "lesson_assistances",
          "tableTo": "user",
          "columnsFrom": [
            "studentId"
          ],
          "columnsTo": [
            "id"
          ],
          "onDelete": "no action",
          "onUpdate": "no action"
        }
      },
      "compositePrimaryKeys": {},
      "uniqueConstraints": {}
    },
    "public.lesson": {
      "name": "lesson",
      "schema": "",
      "columns": {
        "id": {
          "name": "id",
          "type": "varchar(255)",
          "primaryKey": true,
          "notNull": true
        },
        "title": {
          "name": "title",
          "type": "varchar(256)",
          "primaryKey": false,
          "notNull": true
        },
        "description": {
          "name": "description",
          "type": "text",
          "primaryKey": false,
          "notNull": true
        },
        "order": {
          "name": "order",
          "type": "integer",
          "primaryKey": false,
          "notNull": true
        },
        "start_date": {
          "name": "start_date",
          "type": "timestamp with time zone",
          "primaryKey": false,
          "notNull": false
        },
        "new_date": {
          "name": "new_date",
          "type": "timestamp with time zone",
          "primaryKey": false,
          "notNull": false
        },
        "link": {
          "name": "link",
          "type": "varchar",
          "primaryKey": false,
          "notNull": false
        },
        "course_id": {
          "name": "course_id",
          "type": "varchar(255)",
          "primaryKey": false,
          "notNull": false
        },
        "video": {
          "name": "video",
          "type": "varchar(255)",
          "primaryKey": false,
          "notNull": false
        },
        "created_at": {
          "name": "created_at",
          "type": "timestamp with time zone",
          "primaryKey": false,
          "notNull": true,
          "default": "CURRENT_TIMESTAMP"
        },
        "updated_at": {
          "name": "updated_at",
          "type": "timestamp with time zone",
          "primaryKey": false,
          "notNull": false
        }
      },
      "indexes": {},
      "foreignKeys": {
        "lesson_course_id_course_id_fk": {
          "name": "lesson_course_id_course_id_fk",
          "tableFrom": "lesson",
          "tableTo": "course",
          "columnsFrom": [
            "course_id"
          ],
          "columnsTo": [
            "id"
          ],
          "onDelete": "no action",
          "onUpdate": "no action"
        }
      },
      "compositePrimaryKeys": {},
      "uniqueConstraints": {}
    },
    "public.message": {
      "name": "message",
      "schema": "",
      "columns": {
        "id": {
          "name": "id",
          "type": "varchar(255)",
          "primaryKey": true,
          "notNull": true
        },
        "review_id": {
          "name": "review_id",
          "type": "varchar(255)",
          "primaryKey": false,
          "notNull": false
        },
        "sender_id": {
          "name": "sender_id",
          "type": "varchar(255)",
          "primaryKey": false,
          "notNull": true
        },
        "attached_files": {
          "name": "attached_files",
          "type": "text[]",
          "primaryKey": false,
          "notNull": false
        },
        "content": {
          "name": "content",
          "type": "text",
          "primaryKey": false,
          "notNull": false
        },
        "deleted": {
          "name": "deleted",
          "type": "boolean",
          "primaryKey": false,
          "notNull": false,
          "default": false
        },
        "created_at": {
          "name": "created_at",
          "type": "timestamp with time zone",
          "primaryKey": false,
          "notNull": true,
          "default": "CURRENT_TIMESTAMP"
        },
        "updated_at": {
          "name": "updated_at",
          "type": "timestamp with time zone",
          "primaryKey": false,
          "notNull": false
        }
      },
      "indexes": {},
      "foreignKeys": {
        "message_review_id_review_id_fk": {
          "name": "message_review_id_review_id_fk",
          "tableFrom": "message",
          "tableTo": "review",
          "columnsFrom": [
            "review_id"
          ],
          "columnsTo": [
            "id"
          ],
          "onDelete": "cascade",
          "onUpdate": "no action"
        },
        "message_sender_id_user_id_fk": {
          "name": "message_sender_id_user_id_fk",
          "tableFrom": "message",
          "tableTo": "user",
          "columnsFrom": [
            "sender_id"
          ],
          "columnsTo": [
            "id"
          ],
          "onDelete": "no action",
          "onUpdate": "no action"
        }
      },
      "compositePrimaryKeys": {},
      "uniqueConstraints": {}
    },
    "public.mission": {
      "name": "mission",
      "schema": "",
      "columns": {
        "id": {
          "name": "id",
          "type": "varchar(255)",
          "primaryKey": true,
          "notNull": true
        },
        "title": {
          "name": "title",
          "type": "varchar(256)",
          "primaryKey": false,
          "notNull": false
        },
        "instructions": {
          "name": "instructions",
          "type": "text",
          "primaryKey": false,
          "notNull": false
        },
        "lesson_id": {
          "name": "lesson_id",
          "type": "varchar(255)",
          "primaryKey": false,
          "notNull": true
        },
        "score": {
          "name": "score",
          "type": "integer",
          "primaryKey": false,
          "notNull": true,
          "default": 0
        },
        "deadline": {
          "name": "deadline",
          "type": "timestamp with time zone",
          "primaryKey": false,
          "notNull": true
        },
        "created_at": {
          "name": "created_at",
          "type": "timestamp with time zone",
          "primaryKey": false,
          "notNull": true,
          "default": "CURRENT_TIMESTAMP"
        },
        "updated_at": {
          "name": "updated_at",
          "type": "timestamp with time zone",
          "primaryKey": false,
          "notNull": false
        }
      },
      "indexes": {},
      "foreignKeys": {
        "mission_lesson_id_lesson_id_fk": {
          "name": "mission_lesson_id_lesson_id_fk",
          "tableFrom": "mission",
          "tableTo": "lesson",
          "columnsFrom": [
            "lesson_id"
          ],
          "columnsTo": [
            "id"
          ],
          "onDelete": "cascade",
          "onUpdate": "no action"
        }
      },
      "compositePrimaryKeys": {},
      "uniqueConstraints": {}
    },
    "public.notification": {
      "name": "notification",
      "schema": "",
      "columns": {
        "id": {
          "name": "id",
          "type": "varchar(255)",
          "primaryKey": true,
          "notNull": true
        },
        "type": {
          "name": "type",
          "type": "notificationTypes",
          "typeSchema": "public",
          "primaryKey": false,
          "notNull": true
        },
        "is_read": {
          "name": "is_read",
          "type": "boolean",
          "primaryKey": false,
          "notNull": false,
          "default": false
        },
        "user_id": {
          "name": "user_id",
          "type": "varchar(255)",
          "primaryKey": false,
          "notNull": true
        },
        "resource_id": {
          "name": "resource_id",
          "type": "varchar(255)",
          "primaryKey": false,
          "notNull": false
        },
        "content": {
          "name": "content",
          "type": "text",
          "primaryKey": false,
          "notNull": false
        },
        "created_at": {
          "name": "created_at",
          "type": "timestamp with time zone",
          "primaryKey": false,
          "notNull": true,
          "default": "CURRENT_TIMESTAMP"
        },
        "updated_at": {
          "name": "updated_at",
          "type": "timestamp with time zone",
          "primaryKey": false,
          "notNull": false
        }
      },
      "indexes": {},
      "foreignKeys": {
        "notification_user_id_user_id_fk": {
          "name": "notification_user_id_user_id_fk",
          "tableFrom": "notification",
          "tableTo": "user",
          "columnsFrom": [
            "user_id"
          ],
          "columnsTo": [
            "id"
          ],
          "onDelete": "no action",
          "onUpdate": "no action"
        }
      },
      "compositePrimaryKeys": {},
      "uniqueConstraints": {}
    },
    "public.reset_password_token": {
      "name": "reset_password_token",
      "schema": "",
      "columns": {
        "id": {
          "name": "id",
          "type": "varchar(255)",
          "primaryKey": true,
          "notNull": true
        },
        "email": {
          "name": "email",
          "type": "varchar(255)",
          "primaryKey": false,
          "notNull": true
        },
        "token": {
          "name": "token",
          "type": "varchar(255)",
          "primaryKey": false,
          "notNull": true
        },
        "expires": {
          "name": "expires",
          "type": "timestamp with time zone",
          "primaryKey": false,
          "notNull": true
        }
      },
      "indexes": {},
      "foreignKeys": {},
      "compositePrimaryKeys": {},
      "uniqueConstraints": {
        "reset_password_token_token_unique": {
          "name": "reset_password_token_token_unique",
          "nullsNotDistinct": false,
          "columns": [
            "token"
          ]
        }
      }
    },
    "public.review_document": {
      "name": "review_document",
      "schema": "",
      "columns": {
        "id": {
          "name": "id",
          "type": "varchar(255)",
          "primaryKey": true,
          "notNull": true
        },
        "name": {
          "name": "name",
          "type": "varchar(255)",
          "primaryKey": false,
          "notNull": true
        },
        "file_url": {
          "name": "file_url",
          "type": "varchar(255)",
          "primaryKey": false,
          "notNull": true
        },
        "review_id": {
          "name": "review_id",
          "type": "varchar(255)",
          "primaryKey": false,
          "notNull": false
        },
        "solution": {
          "name": "solution",
          "type": "boolean",
          "primaryKey": false,
          "notNull": false,
          "default": false
        },
        "uploaded_by": {
          "name": "uploaded_by",
          "type": "varchar(255)",
          "primaryKey": false,
          "notNull": true
        },
        "created_at": {
          "name": "created_at",
          "type": "timestamp with time zone",
          "primaryKey": false,
          "notNull": true,
          "default": "CURRENT_TIMESTAMP"
        },
        "updated_at": {
          "name": "updated_at",
          "type": "timestamp with time zone",
          "primaryKey": false,
          "notNull": false
        }
      },
      "indexes": {},
      "foreignKeys": {
        "review_document_review_id_review_id_fk": {
          "name": "review_document_review_id_review_id_fk",
          "tableFrom": "review_document",
          "tableTo": "review",
          "columnsFrom": [
            "review_id"
          ],
          "columnsTo": [
            "id"
          ],
          "onDelete": "cascade",
          "onUpdate": "no action"
        },
        "review_document_uploaded_by_user_id_fk": {
          "name": "review_document_uploaded_by_user_id_fk",
          "tableFrom": "review_document",
          "tableTo": "user",
          "columnsFrom": [
            "uploaded_by"
          ],
          "columnsTo": [
            "id"
          ],
          "onDelete": "no action",
          "onUpdate": "no action"
        }
      },
      "compositePrimaryKeys": {},
      "uniqueConstraints": {}
    },
    "public.review": {
      "name": "review",
      "schema": "",
      "columns": {
        "id": {
          "name": "id",
          "type": "varchar(255)",
          "primaryKey": true,
          "notNull": true
        },
        "mission_id": {
          "name": "mission_id",
          "type": "varchar(255)",
          "primaryKey": false,
          "notNull": true
        },
        "subscription_id": {
          "name": "subscription_id",
          "type": "varchar(255)",
          "primaryKey": false,
          "notNull": true
        },
        "extension": {
          "name": "extension",
          "type": "timestamp with time zone",
          "primaryKey": false,
          "notNull": false
        },
        "teacher_review": {
          "name": "teacher_review",
          "type": "text",
          "primaryKey": false,
          "notNull": false
        },
        "score": {
          "name": "score",
          "type": "integer",
          "primaryKey": false,
          "notNull": false
        },
        "created_at": {
          "name": "created_at",
          "type": "timestamp with time zone",
          "primaryKey": false,
          "notNull": true,
          "default": "CURRENT_TIMESTAMP"
        },
        "updated_at": {
          "name": "updated_at",
          "type": "timestamp with time zone",
          "primaryKey": false,
          "notNull": false
        }
      },
      "indexes": {},
      "foreignKeys": {
        "review_mission_id_mission_id_fk": {
          "name": "review_mission_id_mission_id_fk",
          "tableFrom": "review",
          "tableTo": "mission",
          "columnsFrom": [
            "mission_id"
          ],
          "columnsTo": [
            "id"
          ],
          "onDelete": "cascade",
          "onUpdate": "no action"
        },
        "review_subscription_id_subscription_id_fk": {
          "name": "review_subscription_id_subscription_id_fk",
          "tableFrom": "review",
          "tableTo": "subscription",
          "columnsFrom": [
            "subscription_id"
          ],
          "columnsTo": [
            "id"
          ],
          "onDelete": "no action",
          "onUpdate": "no action"
        }
      },
      "compositePrimaryKeys": {},
      "uniqueConstraints": {}
    },
    "public.session": {
      "name": "session",
      "schema": "",
      "columns": {
        "session_token": {
          "name": "session_token",
          "type": "varchar(255)",
          "primaryKey": true,
          "notNull": true
        },
        "user_id": {
          "name": "user_id",
          "type": "varchar(255)",
          "primaryKey": false,
          "notNull": true
        },
        "expires": {
          "name": "expires",
          "type": "timestamp with time zone",
          "primaryKey": false,
          "notNull": true
        }
      },
      "indexes": {
        "session_user_id_idx": {
          "name": "session_user_id_idx",
          "columns": [
            {
              "expression": "user_id",
              "isExpression": false,
              "asc": true,
              "nulls": "last"
            }
          ],
          "isUnique": false,
          "concurrently": false,
          "method": "btree",
          "with": {}
        }
      },
      "foreignKeys": {
        "session_user_id_user_id_fk": {
          "name": "session_user_id_user_id_fk",
          "tableFrom": "session",
          "tableTo": "user",
          "columnsFrom": [
            "user_id"
          ],
          "columnsTo": [
            "id"
          ],
          "onDelete": "no action",
          "onUpdate": "no action"
        }
      },
      "compositePrimaryKeys": {},
      "uniqueConstraints": {}
    },
    "public.subscription": {
      "name": "subscription",
      "schema": "",
      "columns": {
        "id": {
          "name": "id",
          "type": "varchar(255)",
          "primaryKey": true,
          "notNull": true
        },
        "course_id": {
          "name": "course_id",
          "type": "varchar(255)",
          "primaryKey": false,
          "notNull": true
        },
        "student_id": {
          "name": "student_id",
          "type": "varchar(255)",
          "primaryKey": false,
          "notNull": true
        },
        "active": {
          "name": "active",
          "type": "boolean",
          "primaryKey": false,
          "notNull": false,
          "default": true
        },
        "paid": {
          "name": "paid",
          "type": "boolean",
          "primaryKey": false,
          "notNull": false,
          "default": false
        },
        "created_at": {
          "name": "created_at",
          "type": "timestamp with time zone",
          "primaryKey": false,
          "notNull": true,
          "default": "CURRENT_TIMESTAMP"
        },
        "updated_at": {
          "name": "updated_at",
          "type": "timestamp with time zone",
          "primaryKey": false,
          "notNull": false
        }
      },
      "indexes": {},
      "foreignKeys": {
        "subscription_course_id_course_id_fk": {
          "name": "subscription_course_id_course_id_fk",
          "tableFrom": "subscription",
          "tableTo": "course",
          "columnsFrom": [
            "course_id"
          ],
          "columnsTo": [
            "id"
          ],
          "onDelete": "no action",
          "onUpdate": "no action"
        },
        "subscription_student_id_user_id_fk": {
          "name": "subscription_student_id_user_id_fk",
          "tableFrom": "subscription",
          "tableTo": "user",
          "columnsFrom": [
            "student_id"
          ],
          "columnsTo": [
            "id"
          ],
          "onDelete": "no action",
          "onUpdate": "no action"
        }
      },
      "compositePrimaryKeys": {},
      "uniqueConstraints": {}
    },
    "public.user": {
      "name": "user",
      "schema": "",
      "columns": {
        "id": {
          "name": "id",
          "type": "varchar(255)",
          "primaryKey": true,
          "notNull": true
        },
        "name": {
          "name": "name",
          "type": "varchar(255)",
          "primaryKey": false,
          "notNull": false
        },
        "email": {
          "name": "email",
          "type": "varchar(255)",
          "primaryKey": false,
          "notNull": true
        },
        "email_verified": {
          "name": "email_verified",
          "type": "timestamp with time zone",
          "primaryKey": false,
          "notNull": false
        },
        "phone": {
          "name": "phone",
          "type": "varchar(64)",
          "primaryKey": false,
          "notNull": false
        },
        "password": {
          "name": "password",
          "type": "varchar(64)",
          "primaryKey": false,
          "notNull": false
        },
        "role": {
          "name": "role",
          "type": "roles",
          "typeSchema": "public",
          "primaryKey": false,
          "notNull": true,
          "default": "'user'"
        },
        "image": {
          "name": "image",
          "type": "varchar(255)",
          "primaryKey": false,
          "notNull": false
        },
        "created_at": {
          "name": "created_at",
          "type": "timestamp with time zone",
          "primaryKey": false,
          "notNull": true,
          "default": "CURRENT_TIMESTAMP"
        },
        "updated_at": {
          "name": "updated_at",
          "type": "timestamp with time zone",
          "primaryKey": false,
          "notNull": false
        }
      },
      "indexes": {},
      "foreignKeys": {},
      "compositePrimaryKeys": {},
      "uniqueConstraints": {}
    },
    "public.verification_token": {
      "name": "verification_token",
      "schema": "",
      "columns": {
        "id": {
          "name": "id",
          "type": "varchar(255)",
          "primaryKey": true,
          "notNull": true
        },
        "email": {
          "name": "email",
          "type": "varchar(255)",
          "primaryKey": false,
          "notNull": true
        },
        "token": {
          "name": "token",
          "type": "varchar(255)",
          "primaryKey": false,
          "notNull": true
        },
        "expires": {
          "name": "expires",
          "type": "timestamp with time zone",
          "primaryKey": false,
          "notNull": true
        }
      },
      "indexes": {},
      "foreignKeys": {},
      "compositePrimaryKeys": {},
      "uniqueConstraints": {
        "verification_token_token_unique": {
          "name": "verification_token_token_unique",
          "nullsNotDistinct": false,
          "columns": [
            "token"
          ]
        }
      }
    }
  },
  "enums": {
    "public.notificationTypes": {
      "name": "notificationTypes",
      "schema": "public",
      "values": [
        "missionMessage",
        "missionUpdate",
        "reviewScore",
        "reviewExtension",
        "subscriptionUpdate"
      ]
    },
    "public.roles": {
      "name": "roles",
      "schema": "public",
      "values": [
        "user",
        "moderator",
        "admin"
      ]
    }
  },
  "schemas": {},
  "sequences": {},
  "_meta": {
    "columns": {},
    "schemas": {},
    "tables": {}
  }
}